epithet/__init__.py
epithet/epithet.py
epithet-0.0.4.dist-info/DESCRIPTION.rst
epithet-0.0.4.dist-info/METADATA
epithet-0.0.4.dist-info/RECORD
epithet-0.0.4.dist-info/WHEEL
epithet-0.0.4.dist-info/entry_points.txt
epithet-0.0.4.dist-info/metadata.json
epithet-0.0.4.dist-info/top_level.txt
